[
  {
    "rank": 1,
    "owner": "Caro",
    "points": 2,
    "goals": 2,
    "playersWithGoals": 1
  },
  {
    "rank": 2,
    "owner": "Felix",
    "points": 1,
    "goals": 1,
    "playersWithGoals": 1
  },
  {
    "rank": 2,
    "owner": "Jonas",
    "points": 1,
    "goals": 1,
    "playersWithGoals": 1
  },
  {
    "rank": 2,
    "owner": "Marco",
    "points": 1,
    "goals": 1,
    "playersWithGoals": 1
  },
  {
    "rank": 2,
    "owner": "Nina",
    "points": 1,
    "goals": 1,
    "playersWithGoals": 1
  },
  {
    "rank": 2,
    "owner": "Willi",
    "points": 1,
    "goals": 1,
    "playersWithGoals": 1
  },
  {
    "rank": 7,
    "owner": "Anne",
    "points": 0,
    "goals": 0,
    "playersWithGoals": 0
  },
  {
    "rank": 7,
    "owner": "Kim",
    "points": 0,
    "goals": 0,
    "playersWithGoals": 0
  },
  {
    "rank": 7,
    "owner": "Melli",
    "points": 0,
    "goals": 0,
    "playersWithGoals": 0
  },
  {
    "rank": 7,
    "owner": "Peer",
    "points": 0,
    "goals": 0,
    "playersWithGoals": 0
  },
  {
    "rank": 7,
    "owner": "Rafael",
    "points": 0,
    "goals": 0,
    "playersWithGoals": 0
  },
  {
    "rank": 7,
    "owner": "Tjark",
    "points": 0,
    "goals": 0,
    "playersWithGoals": 0
  }
]
