{
  "lastUpdated": "2026-07-05T00:01:45.106Z",
  "source": "api-football",
  "attemptedSources": [
    "api-football"
  ],
  "fallbackUsed": false,
  "status": "ok",
  "goalCount": 381,
  "scoredGoalCount": 43,
  "skippedGoalCount": 0,
  "duplicateGoalCount": 0,
  "sourceErrors": [],
  "message": "Daten-Snapshot mit Quelle api-football erzeugt.",
  "snapshotFingerprint": "90207137f5a79cd2a42382a9bdcf639a7e6dc5c5c0254b6cee68122dbe61747e",
  "snapshotChanged": true,
  "syncWindowId": "football-data:537375-check-2:api-football-enrich:football-data:537375",
  "windowSyncAttempts": 1,
  "liveMatchCount": 0,
  "sourceRequestCount": 3,
  "sourceRequestLimit": 6
}
