{
  "lastUpdated": "2026-06-30T01:31:19.091Z",
  "source": "football-data",
  "attemptedSources": [
    "football-data"
  ],
  "fallbackUsed": false,
  "status": "ok",
  "goalCount": 326,
  "scoredGoalCount": 35,
  "skippedGoalCount": 0,
  "duplicateGoalCount": 0,
  "sourceErrors": [],
  "message": "Daten-Snapshot mit Quelle football-data erzeugt.",
  "snapshotFingerprint": "4a21c55c7d462664d61d6d6f977c8384139fad214ace17430621cfbeb6193d0e",
  "snapshotChanged": true,
  "syncWindowId": "football-data:537418-live",
  "windowSyncAttempts": 1,
  "liveMatchCount": 1,
  "sourceRequestCount": 3,
  "sourceRequestLimit": 6
}
