{
  "lastUpdated": "2026-06-27T02:01:34.394Z",
  "source": "football-data",
  "attemptedSources": [
    "football-data"
  ],
  "fallbackUsed": false,
  "status": "ok",
  "goalCount": 287,
  "scoredGoalCount": 30,
  "skippedGoalCount": 0,
  "duplicateGoalCount": 0,
  "sourceErrors": [],
  "message": "Daten-Snapshot unveraendert (football-data).",
  "snapshotFingerprint": "b5840e2d46ab0fa50a9b7f6b33362f4c44921111d68344779eca9bd751c733ad",
  "snapshotChanged": false,
  "syncWindowId": "2026 fifa world cup group g:egypt-iran:2026-06-27T03:00:00.000Z-pre-match",
  "windowSyncAttempts": 1,
  "liveMatchCount": 2,
  "sourceRequestCount": 4,
  "sourceRequestLimit": 6
}
