{
  "lastUpdated": "2026-07-01T05:01:27.101Z",
  "source": "api-football",
  "attemptedSources": [
    "api-football"
  ],
  "fallbackUsed": false,
  "status": "ok",
  "goalCount": 341,
  "scoredGoalCount": 38,
  "skippedGoalCount": 0,
  "duplicateGoalCount": 0,
  "sourceErrors": [],
  "message": "Daten-Snapshot mit Quelle api-football erzeugt.",
  "snapshotFingerprint": "2d0ba337dc503dd3da7729dc5da1f155eec5d80562e9ca6a21a26d686558669a",
  "snapshotChanged": true,
  "syncWindowId": "football-data:537425-check-3:api-football-enrich:football-data:537425",
  "windowSyncAttempts": 1,
  "liveMatchCount": 0,
  "sourceRequestCount": 3,
  "sourceRequestLimit": 6
}
