{
  "lastUpdated": "2026-07-11T21:31:53.910Z",
  "source": "football-data",
  "attemptedSources": [
    "football-data"
  ],
  "fallbackUsed": false,
  "status": "ok",
  "goalCount": 413,
  "scoredGoalCount": 50,
  "skippedGoalCount": 0,
  "duplicateGoalCount": 0,
  "sourceErrors": [],
  "message": "Daten-Snapshot mit Quelle football-data erzeugt.",
  "snapshotFingerprint": "dbf66c33b44abfe8135e0740910eac963668933f23c74f10bb37b49730ce77e5",
  "snapshotChanged": true,
  "syncWindowId": "football-data:537385-live",
  "windowSyncAttempts": 1,
  "liveMatchCount": 1,
  "sourceRequestCount": 3,
  "sourceRequestLimit": 6
}
